README.md
setup.py
lilymod/__globs__.py
lilymod/__init__.py
lilymod/components.py
lilymod/events.py
lilymod/gfx.py
lilymod/input.py
lilymod/lilymath.py
lilymod/physics.py
lilymod/resource.py
lilymod/version.py
lilymodBETA.egg-info/PKG-INFO
lilymodBETA.egg-info/SOURCES.txt
lilymodBETA.egg-info/dependency_links.txt
lilymodBETA.egg-info/requires.txt
lilymodBETA.egg-info/top_level.txt
lilymod/assets/logo.png
lilymod/pytwin/__init__.py