Metadata-Version: 2.1
Name: lilymodBETA
Version: 1.0.4
Summary: So simple, its criminal
Home-page: https://github.com/d34d0s/Anntwinetta
Author: Izaiyah Stokes
Author-email: zeroth.bat@gmail.com
Classifier: Programming Language :: Python :: 3.12
Classifier: License :: OSI Approved :: MIT License
Classifier: Operating System :: OS Independent
Requires-Dist: GLFW
Requires-Dist: PyGLM
Requires-Dist: PyOpenGL
Requires-Dist: ModernGL
Requires-Dist: Pygame-CE
Requires-Dist: Numpy
Requires-Dist: Numba
Requires-Dist: SetupTools
